MANIFEST.in
README.md
requirements.txt
setup.py
dynamodb_stream_dispatcher/__init__.py
dynamodb_stream_dispatcher/derecord.py
dynamodb_stream_dispatcher/dynamo_stream_dispatcher.py
dynamodb_stream_dispatcher/test_derecord.py
dynamodb_stream_dispatcher.egg-info/PKG-INFO
dynamodb_stream_dispatcher.egg-info/SOURCES.txt
dynamodb_stream_dispatcher.egg-info/dependency_links.txt
dynamodb_stream_dispatcher.egg-info/top_level.txt