Metadata-Version: 1.0
Name: dynamodb-stream-dispatcher
Version: 0.4.1
Summary: Dispatch dymamodb stream event to your functions.
Home-page: https://github.com/higanworks/dynamodb_stream_dispatcher
Author: SAWANOBORI Yukihiko
Author-email: sawanoboriyu@higanworks.com
License: MIT
Platform: UNKNOWN
